main.py
hypixel_stats_bot-0.1.10.dist-info/METADATA
hypixel_stats_bot-0.1.10.dist-info/WHEEL
hypixel_stats_bot-0.1.10.dist-info/entry_points.txt
hypixel_stats_bot-0.1.10.dist-info/top_level.txt
hypixel_stats_bot-0.1.10.dist-info/RECORD
