Metadata-Version: 2.4
Name: hypixel_stats_bot
Version: 0.1.10
Summary: This project lets you quickly view any acount's Hypixel Stats for Bedwars, Skywars, and Slumber Hotel!
Requires-Python: >=3.13.0
Requires-Dist: audioop-lts>=0.2.2
Requires-Dist: py-cord>=2.6.1
Requires-Dist: requests>=2.32.4
Requires-Dist: thefuzz>=0.22.1
